fix_silenced_fixit_error.py
silence_fixit_error.py
silence_fixit_error-0.3.2.dist-info/LICENSE
silence_fixit_error-0.3.2.dist-info/METADATA
silence_fixit_error-0.3.2.dist-info/WHEEL
silence_fixit_error-0.3.2.dist-info/entry_points.txt
silence_fixit_error-0.3.2.dist-info/top_level.txt
silence_fixit_error-0.3.2.dist-info/RECORD
