Metadata-Version: 2.1
Name: silence_fixit_error
Version: 0.3.2
Summary: add `lint-fixme` comments to every occurrence of a `fixit` error
Home-page: https://github.com/samueljsb/silence-fixit-error
Author: Samuel Searles-Bryant
Author-email: sam@samueljsb.co.uk
License: MIT
Classifier: License :: OSI Approved :: MIT License
Classifier: Programming Language :: Python :: 3
Classifier: Programming Language :: Python :: 3 :: Only
Classifier: Programming Language :: Python :: Implementation :: CPython
Requires-Python: >=3.9
License-File: LICENSE
Requires-Dist: fixit >=2.0.0
